{
    "users": [],
    "offers": [],
    "items": [
        {
            "name" : "wood",
            "grade" : 0,
            "price": {
                "money" : 5,
                "ressources": []
            }
        },
        {
            "name" : "iron-oxyde",
            "grade" : 0,
            "price": {
                "money" : 7,
                "ressources": []
            }
        },
        {
            "name" : "iron",
            "grade" : 0,
            "price": {
                "money" : 25,
                "ressources": []
            }
        },
        {
            "name" : "gold",
            "grade" : 1,
            "price": {
                "money" : 200,
                "ressources": []
            }
        }
    ],
    "production-line" : [
        {
            "name" : "iron-desoxydizer",
            "productionStat" : {
                "item" : "iron",
                "production-rate" : "10"
            },
            "grade" : 0,
            "price": {
                "money" : 500,
                "items": [
                    {
                        "item" : "iron-oxyde",
                        "quantity" : 10
                    }
                ]
            }
        }
    ],
    "factory-upgrade" : [
        {
            "name" : "Factory upgrade level 1",
            "grade" : 1,
            "price": {
                "money" : 1000,
                "items": [
                    {
                        "item" : "iron",
                        "quantity" : 100
                    },
                    {
                        "item" : "gold",
                        "quantity" : 500
                    }
                ]
            }
        }
    ]
}